MANIFEST.in
requirements.txt
setup.cfg
setup.py
pagseguro/__init__.py
pagseguro/client.py
pagseguro_sdk.egg-info/PKG-INFO
pagseguro_sdk.egg-info/SOURCES.txt
pagseguro_sdk.egg-info/dependency_links.txt
pagseguro_sdk.egg-info/requires.txt
pagseguro_sdk.egg-info/top_level.txt