Metadata-Version: 1.1
Name: pagseguro-sdk
Version: 0.1.2
Summary: SDK para utilização do PagSeguro em Python
Home-page: http://github.com/jeanmask/pagseguro-sdk/
Author: Jean O. Rodrigues
Author-email: github@jean.bz
License: MIT
Download-URL: https://github.com/jeanmask/pagseguro-sdk/archive/v0.1.2.tar.gz
Keywords: pagseguro,sdk,python
Platform: UNKNOWN
Classifier: Development Status :: 4 - Beta
Classifier: Environment :: Console
Classifier: Environment :: Web Environment
Classifier: Intended Audience :: End Users/Desktop
Classifier: Intended Audience :: Developers
Classifier: Operating System :: OS Independent
Classifier: Programming Language :: Python
Classifier: Topic :: Internet
Classifier: Topic :: Software Development :: Libraries :: Python Modules
